[
    {
        "type": "(n)",
        "mean": "the upper front part of the body between the neck and stomach",
        "examples": [
            {
                "code": "chest_example_that-wrestler-has-a-broad-chest",
                "text": "That wrestler has a broad chest."
            },
            {
                "code": "chest_example_the-actress-was-afraid-to-show-her-bare-chest",
                "text": "The actress was afraid to show her bare chest."
            },
            {
                "code": "chest_example_he-has-a-hairy-chest",
                "text": "He has a hairy chest."
            },
            {
                "code": "chest_example_he-clutched-his-chest-when-he-had-a-heart-attack",
                "text": "He clutched his chest when he had a heart attack."
            },
            {
                "code": "chest_example_the-gorilla-pounded-his-chest",
                "text": "The gorilla pounded his chest."
            },
            {
                "code": "chest_example_do-you-shave-your-chest",
                "text": "Do you shave your chest?"
            },
            {
                "code": "chest_example_the-runner-s-chest-expanded-rapidly",
                "text": "The runner's chest expanded rapidly."
            },
            {
                "code": "chest_example_i-felt-my-chest-tighten",
                "text": "I felt my chest tighten."
            },
            {
                "code": "chest_example_are-you-feeling-any-chest-pain",
                "text": "Are you feeling any chest pain?"
            },
            {
                "code": "chest_example_the-football-player-had-a-chest-injury",
                "text": "The football player had a chest injury."
            },
            {
                "code": "chest_example_the-doctor-is-running-a-chest-x-ray",
                "text": "The doctor is running a chest X-ray."
            },
            {
                "code": "chest_example_those-are-his-chest-muscles",
                "text": "Those are his chest muscles."
            },
            {
                "code": "chest_example_he-injured-his-chest-area",
                "text": "He injured his chest area."
            },
            {
                "code": "chest_example_he-suffered-a-direct-hit-to-his-chest",
                "text": "He suffered a direct hit to his chest."
            },
            {
                "code": "chest_example_he-had-to-shave-the-hair-on-his-chest-for-swimming",
                "text": "He had to shave the hair on his chest for swimming."
            },
            {
                "code": "chest_example_she-experienced-pain-in-her-chest",
                "text": "She experienced pain in her chest."
            }
        ]
    }
]